blawg/__init__.py
blawg/admin.py
blawg/constants.py
blawg/models.py
blawg/urls.py
blawg/utils.py
blawg/static/blawg/css/comment.css
blawg/static/blawg/css/form.css
blawg/static/blawg/css/style.css
blawg/static/blawg/js/comment.js
blawg/static/blawg/js/form.js
blawg/static/blawg/js/jquery-2.1.4.min.js
blawg/static/blawg/js/js.cookie.js
blawg/templates/base.html
blawg/templates/blawg/archive.html
blawg/templates/blawg/base.html
blawg/templates/blawg/blog_confirm_delete.html
blawg/templates/blawg/blog_create.html
blawg/templates/blawg/blog_list.html
blawg/templates/blawg/blog_update.html
blawg/templates/blawg/entry_archive_day.html
blawg/templates/blawg/entry_archive_month.html
blawg/templates/blawg/entry_archive_year.html
blawg/templates/blawg/entry_confirm_delete.html
blawg/templates/blawg/entry_create.html
blawg/templates/blawg/entry_detail.html
blawg/templates/blawg/entry_list.html
blawg/templates/blawg/entry_update.html
blawg/templates/blawg/form.html
django_blawg-0.0.1.dist-info/DESCRIPTION.rst
django_blawg-0.0.1.dist-info/METADATA
django_blawg-0.0.1.dist-info/RECORD
django_blawg-0.0.1.dist-info/WHEEL
django_blawg-0.0.1.dist-info/metadata.json
django_blawg-0.0.1.dist-info/top_level.txt
