Metadata-Version: 2.0
Name: django-blawg
Version: 0.0.1
Summary: Simple blogging application
Home-page: https://github.com/amikrop/django-blawg
Author: Aristotelis Mikropoulos
Author-email: amikrop@gmail.com
License: BSD
Download-URL: https://github.com/amikrop/django-blawg
Platform: UNKNOWN
Classifier: Environment :: Web Environment
Classifier: Framework :: Django
Classifier: Intended Audience :: Developers
Classifier: Intended Audience :: End Users/Desktop
Classifier: License :: OSI Approved :: BSD License
Classifier: Operating System :: OS Independent
Classifier: Programming Language :: Python
Classifier: Topic :: Internet :: WWW/HTTP
Classifier: Topic :: Internet :: WWW/HTTP :: Dynamic Content
Classifier: Topic :: Internet :: WWW/HTTP :: Dynamic Content :: News/Diary
Requires-Dist: Django (>=1.9)
Requires-Dist: django-autoslug (>=1.9)
Requires-Dist: django-mptt (>=0.8)
